clevercloud/CleverClean.py
clevercloud/CleverLemStem.py
clevercloud/CleverStopwords.py
clevercloud/CleverWordCloud.py
clevercloud/__init__.py
clevercloud-0.1.4.dist-info/LICENSE
clevercloud-0.1.4.dist-info/WHEEL
clevercloud-0.1.4.dist-info/METADATA
clevercloud-0.1.4.dist-info/RECORD
