Metadata-Version: 2.1
Name: clevercloud
Version: 0.1.4
Summary: A package for creating clever word clouds
License: MIT
Author: Group_20
Requires-Python: >=3.9,<4.0
Classifier: License :: OSI Approved :: MIT License
Classifier: Programming Language :: Python :: 3
Classifier: Programming Language :: Python :: 3.10
Classifier: Programming Language :: Python :: 3.9
Requires-Dist: nltk (>=3.6.7,<4.0.0)
Requires-Dist: pandas (>=1.3.5,<2.0.0)
Requires-Dist: stem (>=1.8.0,<2.0.0)
Requires-Dist: wordcloud (>=1.8.1,<2.0.0)
